boldi/_build_version.py
boldi/build.py
boldi_build-0.9.7.dist-info/METADATA
boldi_build-0.9.7.dist-info/WHEEL
boldi_build-0.9.7.dist-info/RECORD
